README.txt
setup.cfg
setup.py
pydataportability/__init__.py
pydataportability.xrds.egg-info/PKG-INFO
pydataportability.xrds.egg-info/SOURCES.txt
pydataportability.xrds.egg-info/dependency_links.txt
pydataportability.xrds.egg-info/entry_points.txt
pydataportability.xrds.egg-info/namespace_packages.txt
pydataportability.xrds.egg-info/not-zip-safe
pydataportability.xrds.egg-info/requires.txt
pydataportability.xrds.egg-info/top_level.txt
pydataportability/xrds/__init__.py
pydataportability/xrds/parser.py
pydataportability/xrds/tests/__init__.py
pydataportability/xrds/tests/conftest.py
pydataportability/xrds/tests/test_xrds.py