Metadata-Version: 1.0
Name: pydataportability.xrds
Version: 0.2
Summary: An XRDS parser
Home-page: http://mrtopf.de/blog
Author: Christian Scholz
Author-email: cs@comlounge.net
License: BSD
Keywords: dataportability xrds simple parser
Platform: UNKNOWN
Classifier: Programming Language :: Python
Classifier: Topic :: Software Development :: Libraries :: Python Modules
